dj_editor_js-0.1.1.dist-info/licenses/LICENSE
editor_js/__init__.py
editor_js/apps.py
editor_js/config.py
editor_js/fields.py
editor_js/models.py
editor_js/renderers.py
editor_js/urls.py
editor_js/views.py
editor_js/widgets.py
editor_js/migrations/__init__.py
editor_js/static/editor_js/css/editor_js_admin.css
editor_js/static/editor_js/js/editor_js_iframe.js
editor_js/static/editor_js/js/editor_js_widget.js
editor_js/static/editor_js/js/plugins/button-tool.js
editor_js/static/editor_js/js/plugins/divider-tool.js
editor_js/templates/editor_js/editor_js_iframe.html
editor_js/templates/editor_js/admin/widgets/editor_js_widget.html
editor_js/templatetags/editor_js_filters.py
dj_editor_js-0.1.1.dist-info/METADATA
dj_editor_js-0.1.1.dist-info/WHEEL
dj_editor_js-0.1.1.dist-info/top_level.txt
dj_editor_js-0.1.1.dist-info/RECORD
