Metadata-Version: 2.4
Name: dj-editor-js
Version: 0.1.1
Summary: A Django library to integrate the Editor.js editor with image handling and custom tools.
Author-email: Otto <opensource@otto.srl>
License: MIT License
Project-URL: Homepage, https://github.com/otto-torino/django-editor-js
Project-URL: Repository, https://github.com/otto-torino/django-editor-js
Project-URL: Bug Tracker, https://github.com/otto-torino/django-editor-js/issues
Classifier: Environment :: Web Environment
Classifier: Framework :: Django
Classifier: Framework :: Django :: 4.2
Classifier: Framework :: Django :: 5.0
Classifier: Intended Audience :: Developers
Classifier: License :: OSI Approved :: MIT License
Classifier: Operating System :: OS Independent
Classifier: Programming Language :: Python
Classifier: Programming Language :: Python :: 3
Classifier: Programming Language :: Python :: 3.8
Classifier: Programming Language :: Python :: 3.9
Classifier: Programming Language :: Python :: 3.10
Classifier: Programming Language :: Python :: 3.11
Requires-Python: >=3.8
License-File: LICENSE
Requires-Dist: Django>=3.2
Dynamic: license-file
